scrapy_selenium/__init__.py
scrapy_selenium/http.py
scrapy_selenium/middlewares.py
scrapy_selenium2-0.0.8.dist-info/LICENCE
scrapy_selenium2-0.0.8.dist-info/METADATA
scrapy_selenium2-0.0.8.dist-info/WHEEL
scrapy_selenium2-0.0.8.dist-info/top_level.txt
scrapy_selenium2-0.0.8.dist-info/RECORD
