Metadata-Version: 2.1
Name: scrapy-selenium2
Version: 0.0.8
Summary: Scrapy with selenium
Home-page: https://github.com/clemfromspace/scrapy-selenium
Author: Clément Denoix
Author-email: clement.denoix@gmail.com
License: BSD
Requires-Python: >=3.8
License-File: LICENCE
Requires-Dist: scrapy !=2.4.0,>=2.0
Requires-Dist: selenium >=4.18.1
